moceris/__init__.py
moceris/console/Apple_Hei_packed.py
moceris/console/__init__.py
moceris/console/border.py
moceris/console/console.py
moceris/console/mocio.py
moceris/console/ui.py
moceris/console/wordtile.py
moceris/tools/__init__.py
moceris/tools/bin2py.py
libmoceris-0.0.12.dist-info/METADATA
libmoceris-0.0.12.dist-info/WHEEL
libmoceris-0.0.12.dist-info/top_level.txt
libmoceris-0.0.12.dist-info/RECORD
