Metadata-Version: 2.1
Name: libmoceris
Version: 0.0.12
Summary: MOCERIS Gaming Engine
Home-page: https://gitee.com/moceris-studio/libmoceris
Author: MOCERIS STUDIO
Author-email: MocerisStudio@outlook.com
License: UNKNOWN
Platform: any
Classifier: Programming Language :: Python :: 3
Classifier: License :: OSI Approved :: MIT License
Classifier: Operating System :: OS Independent
